faisst_denstream/DenStream.py
faisst_denstream/MicroCluster.py
faisst_denstream/__init__.py
faisst_denstream-0.0.8.dist-info/METADATA
faisst_denstream-0.0.8.dist-info/WHEEL
faisst_denstream-0.0.8.dist-info/licenses/LICENSE
faisst_denstream-0.0.8.dist-info/RECORD
