Metadata-Version: 2.4
Name: faisst-denstream
Version: 0.0.8
Summary: A performant implementation of the DenStream algorithm that relies heavily on FAISS
Project-URL: Homepage, https://github.com/StateFromJakeFarm/faisst-denstream
Project-URL: Issues, https://github.com/StateFromJakeFarm/faisst-denstream/issues
Author-email: Jake Hansen <jakehansendev@proton.me>
License-Expression: Apache-2.0
License-File: LICENSE
Classifier: Operating System :: OS Independent
Classifier: Programming Language :: Python :: 3
Requires-Python: >=3.11
Requires-Dist: faiss-cpu
Requires-Dist: loguru
Requires-Dist: numpy
Requires-Dist: scikit-learn
Provides-Extra: gpu-cu11
Requires-Dist: faiss-gpu-cu11; extra == 'gpu-cu11'
Provides-Extra: gpu-cu12
Requires-Dist: faiss-gpu-cu12; extra == 'gpu-cu12'
